afsm/__init__.py
afsm/afsm.py
afsm/state_base.py
afsm/test/test_afsm.py
afsm-0.1.4.dist-info/licenses/LICENSE
afsm-0.1.4.dist-info/METADATA
afsm-0.1.4.dist-info/WHEEL
afsm-0.1.4.dist-info/top_level.txt
afsm-0.1.4.dist-info/RECORD
