Metadata-Version: 2.4
Name: afsm
Version: 0.1.4
Summary: Async-aware documentation-first Finite State Machine."
Author-email: Aleksei Romanenko <aleksei.romanenko@lut.fi>
License-Expression: LGPL-2.1-or-later
Project-URL: Homepage, https://github.com/Kreastr/afsm
Project-URL: Issues, https://github.com/Kreastr/afsm/issues
Keywords: fsm,finite,state,machine,async,UML,PlantUML
Classifier: Programming Language :: Python :: 3
Classifier: Operating System :: OS Independent
Requires-Python: >=3.12
License-File: LICENSE
Requires-Dist: pyee
Requires-Dist: beartype
Requires-Dist: python-slugify
Requires-Dist: ply
Dynamic: license-file
